epythets
