Metadata-Version: 2.1
Name: epythets
Version: 0.2.5
Summary: С помощью pymorphy извлекаем из текстов множества эпитетов, нормализуем и сохраняем их в БД sqlite.
Home-page: https://github.com/strizhechenko/epythets
Author: Oleg Strizhechenko
Author-email: oleg.strizhechenko@gmail.com
License: MIT
Platform: UNKNOWN
Requires-Python: >=3.8.0
